{
  "TRAIN_NO": "12841",
  "TRAIN_COACH": "3A",
  "TRAVEL_DATE": "28/04/2025",
  "SOURCE_STATION": "HWH",
  "BOARDING_STATION": null,
  "DESTINATION_STATION": "MS",
  "TATKAL": true,
  "PREMIUM_TATKAL": false,
  "UPI_ID_CONFIG": "",
  "PASSENGER_DETAILS": [
    {
      "NAME": "Shivam Pandey",
      "AGE": 26,
      "GENDER": "Male",
      "SEAT": "No Preference",
      "FOOD": "No Food"
    },
    {
      "NAME": "Shivam Dubey",
      "AGE": 26,
      "GENDER": "Female",
      "SEAT": "No Preference",
      "FOOD": "No Food"
    }
  ],
  "__valid_coaches__": "3A",
  "__valid_seats__": "No Preference",
  "__valid_genders__": "Male",
  "__valid_food_choices__": "No Food"
}
